django_simple_blog-0.3.0.dist-info/METADATA
django_simple_blog-0.3.0.dist-info/RECORD
django_simple_blog-0.3.0.dist-info/WHEEL
django_simple_blog-0.3.0.dist-info/top_level.txt
simpleblog/__init__.py
simpleblog/admin.py
simpleblog/forms.py
simpleblog/models.py
simpleblog/settings.py
simpleblog/signals.py
simpleblog/tests.py
simpleblog/urls.py
simpleblog/views.py
simpleblog/locale/fr_FR/LC_MESSAGES/django.mo
simpleblog/locale/fr_FR/LC_MESSAGES/django.po
simpleblog/locale/sv_SE/LC_MESSAGES/django.mo
simpleblog/locale/sv_SE/LC_MESSAGES/django.po
simpleblog/migrations/0001_initial.py
simpleblog/migrations/__init__.py
simpleblog/templates/simpleblog/post_archive.html
simpleblog/templates/simpleblog/post_archive_page.html
simpleblog/templates/simpleblog/post_detail.html
simpleblog/templates/simpleblog/post_detail_page.html
simpleblog/templates/simpleblog/post_list.html
simpleblog/templates/simpleblog/post_list_page.html
simpleblog/templates/simpleblog/includes/post_form.html
simpleblog/templates/tags/latest_blog_posts.html
simpleblog/templatetags/__init__.py
simpleblog/templatetags/blog_tags.py
