Metadata-Version: 2.1
Name: django-simple-blog
Version: 0.3.0
Summary: An easy way to start writing blog posts.
Home-page: https://github.com/Drager/django-simple-blog
Author: Drager
Author-email: drager@programmers.se
License: BSD License
Platform: UNKNOWN
Classifier: Environment :: Web Environment
Classifier: Framework :: Django
Classifier: Intended Audience :: Developers
Classifier: License :: OSI Approved :: BSD License
Classifier: Programming Language :: Python
Classifier: Programming Language :: Python :: 2.6
Classifier: Programming Language :: Python :: 2.7
Classifier: Programming Language :: Python :: 3.4
Classifier: Programming Language :: Python :: 3.5
Classifier: Topic :: Internet :: WWW/HTTP
Classifier: Topic :: Internet :: WWW/HTTP :: Dynamic Content
Requires-Dist: Django (>=1.8)
Requires-Dist: django-el-pagination (==3.0.1)
Requires-Dist: django-simple-math-captcha (>=1.0.3)
Requires-Dist: django-markdown-deux (>=1.0.4)
Requires-Dist: django-pagedown (>=0.0.5)
